{
    "keyword": "assembly",
    "searchableSites": [
        "karlancer",
        "ponisha",
        "jobinja",
        "jobvision"
    ],
    "jobs": [
        {
            "type": "jobinja",
            "url": "https://jobinja.ir/companies/research-center-of-informatic-industries/jobs/t62r/%D8%A7%D8%B3%D8%AA%D8%AE%D8%AF%D8%A7%D9%85-%DA%A9%D8%A7%D8%B1%D8%B4%D9%86%D8%A7%D8%B3-%D8%A2%D9%86%D8%A7%D9%84%DB%8C%D8%B2-%D8%A8%D8%AF%D8%A7%D9%81%D8%B2%D8%A7%D8%B1-%D8%AF%D8%B1-%D9%85%D8%B1%DA%A9%D8%B2-%D8%AA%D8%AD%D9%82%DB%8C%D9%82%D8%A7%D8%AA-%D8%B5%D9%86%D8%A7%DB%8C%D8%B9-%D8%A7%D9%86%D9%81%D9%88%D8%B1%D9%85%D8%A7%D8%AA%DB%8C%DA%A9?_ref=16&_t=352e3132322e35382e3630",
            "title": "کارشناس آنالیز بدافزار",
            "caption": null,
            "salary": -1,
            "salaryStart": -1,
            "salaryEnd": -1,
            "image": null,
            "time": "۲ روز پیش",
            "owner": "مرکز تحقیقات صنایع انفورماتیک | Research Center",
            "location": "تهران، تهران",
            "jobType": "قرارداد تمام‌وقت",
            "id": "https://jobinja.ir/companies/research-center-of-informatic-industries/jobs/t62r/%D8%A7%D8%B3%D8%AA%D8%AE%D8%AF%D8%A7%D9%85-%DA%A9%D8%A7%D8%B1%D8%B4%D9%86%D8%A7%D8%B3-%D8%A2%D9%86%D8%A7%D9%84%DB%8C%D8%B2-%D8%A8%D8%AF%D8%A7%D9%81%D8%B2%D8%A7%D8%B1-%D8%AF%D8%B1-%D9%85%D8%B1%DA%A9%D8%B2-%D8%AA%D8%AD%D9%82%DB%8C%D9%82%D8%A7%D8%AA-%D8%B5%D9%86%D8%A7%DB%8C%D8%B9-%D8%A7%D9%86%D9%81%D9%88%D8%B1%D9%85%D8%A7%D8%AA%DB%8C%DA%A9?_ref=16&_t=352e3132322e35382e3630"
        },
        {
            "type": "jobvision",
            "url": "https://jobvision.ir/jobs/1068140/استخدام-کارشناس-ارشد-نرم-افزار?row=1&pageSize=30&keyword=assembly&searchId=389247997190924757&score=22.212619779999997&ReferrerJobPosition=8",
            "title": "کارشناس ارشد نرم افزار",
            "caption": null,
            "salary": 0,
            "salaryStart": 0,
            "salaryEnd": 0,
            "image": null,
            "time": "8 روز پیش",
            "owner": "صدراگستر",
            "location": "تهران",
            "jobType": null,
            "id": "https://jobvision.ir/jobs/1068140/استخدام-کارشناس-ارشد-نرم-افزار?row=1&pageSize=30&keyword=assembly&searchId=389247997190924757&score=22.212619779999997&ReferrerJobPosition=8"
        },
        {
            "type": "jobvision",
            "url": "https://jobvision.ir/jobs/1158080/استخدام-کارشناس-تحقیق-و-توسعه-الکترونیک?row=2&pageSize=30&keyword=assembly&searchId=389247997190924757&score=18.298936370000003&ReferrerJobPosition=8",
            "title": "کارشناس تحقیق و توسعه (الکترونیک)",
            "caption": null,
            "salary": 0,
            "salaryStart": 0,
            "salaryEnd": 0,
            "image": "https://jobvision.ir/assets/images/jobs/close-white.svg",
            "time": "18 روز پیش",
            "owner": "هلدینگ فناوری نوآوری آراد",
            "location": "تهران",
            "jobType": "امکان دورکاری",
            "id": "https://jobvision.ir/jobs/1158080/استخدام-کارشناس-تحقیق-و-توسعه-الکترونیک?row=2&pageSize=30&keyword=assembly&searchId=389247997190924757&score=18.298936370000003&ReferrerJobPosition=8"
        },
        {
            "type": "jobvision",
            "url": "https://jobvision.ir/jobs/1152518/استخدام-برنامه-نویس-میکروکنترلر?row=3&pageSize=30&keyword=assembly&searchId=389247997190924757&score=13.264152590000002&ReferrerJobPosition=8",
            "title": "برنامه نویس میکروکنترلر",
            "caption": null,
            "salary": 0,
            "salaryStart": 0,
            "salaryEnd": 0,
            "image": null,
            "time": "44 روز پیش",
            "owner": "گروه مهندسی شهاب",
            "location": "قم",
            "jobType": null,
            "id": "https://jobvision.ir/jobs/1152518/استخدام-برنامه-نویس-میکروکنترلر?row=3&pageSize=30&keyword=assembly&searchId=389247997190924757&score=13.264152590000002&ReferrerJobPosition=8"
        },
        {
            "type": "jobvision",
            "url": "https://jobvision.ir/jobs/1157450/استخدام-کارشناس-مکانیک---آقا?row=4&pageSize=30&keyword=assembly&searchId=389247997190924757&score=6.9351644404&ReferrerJobPosition=8",
            "title": "کارشناس مکانیک - آقا",
            "caption": null,
            "salary": 25000000,
            "salaryStart": 25000000,
            "salaryEnd": 30000000,
            "image": null,
            "time": "11 روز پیش",
            "owner": "زاگرس صنعت آرکا",
            "location": "رباط کریم",
            "jobType": null,
            "id": "https://jobvision.ir/jobs/1157450/استخدام-کارشناس-مکانیک---آقا?row=4&pageSize=30&keyword=assembly&searchId=389247997190924757&score=6.9351644404&ReferrerJobPosition=8"
        },
        {
            "type": "jobvision",
            "url": "https://jobvision.ir/jobs/1165547/استخدام-نقشه-کش-صنعتی---خانم?row=5&pageSize=30&keyword=assembly&searchId=389247997190924757&score=7.343455527400001&ReferrerJobPosition=8",
            "title": "نقشه کش صنعتی - خانم",
            "caption": null,
            "salary": 20000000,
            "salaryStart": 20000000,
            "salaryEnd": 30000000,
            "image": null,
            "time": "5 روز پیش",
            "owner": "پرشین ولف فیتنس",
            "location": "گرمدره",
            "jobType": null,
            "id": "https://jobvision.ir/jobs/1165547/استخدام-نقشه-کش-صنعتی---خانم?row=5&pageSize=30&keyword=assembly&searchId=389247997190924757&score=7.343455527400001&ReferrerJobPosition=8"
        },
        {
            "type": "jobvision",
            "url": "https://jobvision.ir/jobs/1155525/استخدام-کارشناس-نرم‌-افزار-embedded?row=6&pageSize=30&keyword=assembly&searchId=389247997190924757&score=12.786945719&ReferrerJobPosition=8",
            "title": "کارشناس نرم‌ افزار (Embedded)",
            "caption": null,
            "salary": 0,
            "salaryStart": 0,
            "salaryEnd": 0,
            "image": null,
            "time": "41 روز پیش",
            "owner": "الکتروپیک",
            "location": "تهران",
            "jobType": null,
            "id": "https://jobvision.ir/jobs/1155525/استخدام-کارشناس-نرم‌-افزار-embedded?row=6&pageSize=30&keyword=assembly&searchId=389247997190924757&score=12.786945719&ReferrerJobPosition=8"
        },
        {
            "type": "jobvision",
            "url": "https://jobvision.ir/jobs/1070223/استخدام-کارشناس-مهندسی-ساخت-و-تولید?row=7&pageSize=30&keyword=assembly&searchId=389247997190924757&score=6.268383443&ReferrerJobPosition=8",
            "title": "کارشناس مهندسی ساخت و تولید",
            "caption": null,
            "salary": 0,
            "salaryStart": 0,
            "salaryEnd": 0,
            "image": "https://fileapi.jobvision.ir/StaticFiles/Employer/DefaultImages/default-companyLogo.png?v=20231122",
            "time": "10 روز پیش",
            "owner": "سازمانی فعال در حوزه خدمات مهندسی و تخصصی",
            "location": "احمدآباد مستوفی",
            "jobType": null,
            "id": "https://jobvision.ir/jobs/1070223/استخدام-کارشناس-مهندسی-ساخت-و-تولید?row=7&pageSize=30&keyword=assembly&searchId=389247997190924757&score=6.268383443&ReferrerJobPosition=8"
        },
        {
            "type": "jobvision",
            "url": "https://jobvision.ir/jobs/1054094/استخدام-کارشناس-نقشه-کشی-صنعتی?row=8&pageSize=30&keyword=assembly&searchId=389247997190924757&score=6.514968708800001&ReferrerJobPosition=8",
            "title": "کارشناس نقشه کشی صنعتی",
            "caption": null,
            "salary": 0,
            "salaryStart": 0,
            "salaryEnd": 0,
            "image": null,
            "time": "10 روز پیش",
            "owner": "شرکت سرو هیدرولیک پویا",
            "location": "احمدآباد مستوفی",
            "jobType": null,
            "id": "https://jobvision.ir/jobs/1054094/استخدام-کارشناس-نقشه-کشی-صنعتی?row=8&pageSize=30&keyword=assembly&searchId=389247997190924757&score=6.514968708800001&ReferrerJobPosition=8"
        },
        {
            "type": "jobvision",
            "url": "https://jobvision.ir/jobs/1160393/استخدام-برنامه-نویس-embedded-سیستم-های-نهفته?row=9&pageSize=30&keyword=assembly&searchId=389247997190924757&score=11.429646780999999&ReferrerJobPosition=8",
            "title": "برنامه نویس Embedded (سیستم های نهفته)",
            "caption": null,
            "salary": 45000000,
            "salaryStart": 45000000,
            "salaryEnd": 55000000,
            "image": null,
            "time": "36 روز پیش",
            "owner": "باسط پژوه تهران",
            "location": "تهران",
            "jobType": null,
            "id": "https://jobvision.ir/jobs/1160393/استخدام-برنامه-نویس-embedded-سیستم-های-نهفته?row=9&pageSize=30&keyword=assembly&searchId=389247997190924757&score=11.429646780999999&ReferrerJobPosition=8"
        },
        {
            "type": "jobvision",
            "url": "https://jobvision.ir/jobs/1165040/استخدام-طراح-صنعتی?row=10&pageSize=30&keyword=assembly&searchId=389247997190924757&score=4.8114940376&ReferrerJobPosition=8",
            "title": "طراح صنعتی",
            "caption": null,
            "salary": 25000000,
            "salaryStart": 25000000,
            "salaryEnd": 35000000,
            "image": null,
            "time": "10 روز پیش",
            "owner": "افق توسعه",
            "location": "تهران",
            "jobType": null,
            "id": "https://jobvision.ir/jobs/1165040/استخدام-طراح-صنعتی?row=10&pageSize=30&keyword=assembly&searchId=389247997190924757&score=4.8114940376&ReferrerJobPosition=8"
        },
        {
            "type": "jobvision",
            "url": "https://jobvision.ir/jobs/1188409/استخدام-مهندس-مکانیک?row=11&pageSize=30&keyword=assembly&searchId=389247997190924757&score=5.1622420025&ReferrerJobPosition=8",
            "title": "مهندس مکانیک",
            "caption": null,
            "salary": 20000000,
            "salaryStart": 20000000,
            "salaryEnd": 30000000,
            "image": null,
            "time": "دیروز",
            "owner": "گروه صنعتی سیفی",
            "location": "پاکدشت",
            "jobType": null,
            "id": "https://jobvision.ir/jobs/1188409/استخدام-مهندس-مکانیک?row=11&pageSize=30&keyword=assembly&searchId=389247997190924757&score=5.1622420025&ReferrerJobPosition=8"
        },
        {
            "type": "jobvision",
            "url": "https://jobvision.ir/jobs/1180234/استخدام-مدیر-تحقیق-و-توسعه?row=12&pageSize=30&keyword=assembly&searchId=389247997190924757&score=4.1652052416&ReferrerJobPosition=8",
            "title": "مدیر تحقیق و توسعه",
            "caption": null,
            "salary": 0,
            "salaryStart": 0,
            "salaryEnd": 0,
            "image": null,
            "time": "دیروز",
            "owner": "سرمایه زرین ایرانیان آرنا",
            "location": "تهران",
            "jobType": null,
            "id": "https://jobvision.ir/jobs/1180234/استخدام-مدیر-تحقیق-و-توسعه?row=12&pageSize=30&keyword=assembly&searchId=389247997190924757&score=4.1652052416&ReferrerJobPosition=8"
        },
        {
            "type": "jobvision",
            "url": "https://jobvision.ir/jobs/1141406/استخدام-کارشناس-نقشه-کشی-صنعتی?row=13&pageSize=30&keyword=assembly&searchId=389247997190924757&score=2.357821&ReferrerJobPosition=8",
            "title": "کارشناس نقشه کشی صنعتی",
            "caption": null,
            "salary": 25000000,
            "salaryStart": 25000000,
            "salaryEnd": 30000000,
            "image": null,
            "time": "38 روز پیش",
            "owner": "واحد طراحی و تکنولوژی",
            "location": "تهران",
            "jobType": null,
            "id": "https://jobvision.ir/jobs/1141406/استخدام-کارشناس-نقشه-کشی-صنعتی?row=13&pageSize=30&keyword=assembly&searchId=389247997190924757&score=2.357821&ReferrerJobPosition=8"
        },
        {
            "type": "jobvision",
            "url": "https://jobvision.ir/jobs/1185706/استخدام-مهندس-مکانیک?row=14&pageSize=30&keyword=assembly&searchId=389247997190924757&score=5.8517319599999995&ReferrerJobPosition=8",
            "title": "مهندس مکانیک",
            "caption": null,
            "salary": 0,
            "salaryStart": 0,
            "salaryEnd": 0,
            "image": null,
            "time": "3 روز پیش",
            "owner": "خلق ایده شوان",
            "location": "پاکدشت",
            "jobType": null,
            "id": "https://jobvision.ir/jobs/1185706/استخدام-مهندس-مکانیک?row=14&pageSize=30&keyword=assembly&searchId=389247997190924757&score=5.8517319599999995&ReferrerJobPosition=8"
        },
        {
            "type": "jobvision",
            "url": "https://jobvision.ir/jobs/1032652/استخدام-کارشناس-مهندسی-ساخت-طراحی-فیکسچر?row=15&pageSize=30&keyword=assembly&searchId=389247997190924757&score=5.827268576000001&ReferrerJobPosition=8",
            "title": "کارشناس مهندسی ساخت (طراحی فیکسچر)",
            "caption": null,
            "salary": 0,
            "salaryStart": 0,
            "salaryEnd": 0,
            "image": null,
            "time": "10 روز پیش",
            "owner": "شرکت سرو هیدرولیک پویا",
            "location": "احمدآباد مستوفی",
            "jobType": null,
            "id": "https://jobvision.ir/jobs/1032652/استخدام-کارشناس-مهندسی-ساخت-طراحی-فیکسچر?row=15&pageSize=30&keyword=assembly&searchId=389247997190924757&score=5.827268576000001&ReferrerJobPosition=8"
        },
        {
            "type": "jobvision",
            "url": "https://jobvision.ir/jobs/1187278/استخدام-مهندس-مکانیک-طراحی-جامدات---آقا?row=16&pageSize=30&keyword=assembly&searchId=389247997190924757&score=5.4792548839999995&ReferrerJobPosition=8",
            "title": "مهندس مکانیک (طراحی جامدات) - آقا",
            "caption": null,
            "salary": 25000000,
            "salaryStart": 25000000,
            "salaryEnd": 35000000,
            "image": null,
            "time": "3 روز پیش",
            "owner": "ریل پرداز سیستم",
            "location": "تهران",
            "jobType": null,
            "id": "https://jobvision.ir/jobs/1187278/استخدام-مهندس-مکانیک-طراحی-جامدات---آقا?row=16&pageSize=30&keyword=assembly&searchId=389247997190924757&score=5.4792548839999995&ReferrerJobPosition=8"
        },
        {
            "type": "jobvision",
            "url": "https://jobvision.ir/jobs/1165959/استخدام-production-manager?row=17&pageSize=30&keyword=assembly&searchId=389247997190924757&score=5.146639840000001&ReferrerJobPosition=8",
            "title": "Production manager",
            "caption": null,
            "salary": 0,
            "salaryStart": 0,
            "salaryEnd": 0,
            "image": null,
            "time": "29 روز پیش",
            "owner": "دیجی کالا",
            "location": "تهران",
            "jobType": null,
            "id": "https://jobvision.ir/jobs/1165959/استخدام-production-manager?row=17&pageSize=30&keyword=assembly&searchId=389247997190924757&score=5.146639840000001&ReferrerJobPosition=8"
        },
        {
            "type": "jobvision",
            "url": "https://jobvision.ir/jobs/1180683/استخدام-مهندس-نمونه‌سازی-و-انتقال-به-تولید?row=18&pageSize=30&keyword=assembly&searchId=389247997190924757&score=4.7167301558&ReferrerJobPosition=8",
            "title": "مهندس نمونه‌سازی و انتقال به تولید",
            "caption": null,
            "salary": 25000000,
            "salaryStart": 25000000,
            "salaryEnd": 30000000,
            "image": null,
            "time": "9 روز پیش",
            "owner": "اف جی",
            "location": "نظر آباد",
            "jobType": null,
            "id": "https://jobvision.ir/jobs/1180683/استخدام-مهندس-نمونه‌سازی-و-انتقال-به-تولید?row=18&pageSize=30&keyword=assembly&searchId=389247997190924757&score=4.7167301558&ReferrerJobPosition=8"
        },
        {
            "type": "jobvision",
            "url": "https://jobvision.ir/jobs/1157960/استخدام-مهندس-مکانیک-طراحی?row=19&pageSize=30&keyword=assembly&searchId=389247997190924757&score=4.120938&ReferrerJobPosition=8",
            "title": "مهندس مکانیک طراحی",
            "caption": null,
            "salary": 0,
            "salaryStart": 0,
            "salaryEnd": 0,
            "image": "https://fileapi.jobvision.ir/StaticFiles/Employer/DefaultImages/default-companyLogo.png?v=20231122",
            "time": "38 روز پیش",
            "owner": "سازمانی فعال در حوزه نفت، گاز و پتروشیمی",
            "location": "تهران",
            "jobType": null,
            "id": "https://jobvision.ir/jobs/1157960/استخدام-مهندس-مکانیک-طراحی?row=19&pageSize=30&keyword=assembly&searchId=389247997190924757&score=4.120938&ReferrerJobPosition=8"
        },
        {
            "type": "jobvision",
            "url": "https://jobvision.ir/jobs/1146379/استخدام-مهندس-مکانیک---آقا?row=20&pageSize=30&keyword=assembly&searchId=389247997190924757&score=3.3668063459999997&ReferrerJobPosition=8",
            "title": "مهندس مکانیک - آقا",
            "caption": null,
            "salary": 20000000,
            "salaryStart": 20000000,
            "salaryEnd": 30000000,
            "image": null,
            "time": "51 روز پیش",
            "owner": "آدرین پژوهش معدن سجاد",
            "location": "تهران",
            "jobType": null,
            "id": "https://jobvision.ir/jobs/1146379/استخدام-مهندس-مکانیک---آقا?row=20&pageSize=30&keyword=assembly&searchId=389247997190924757&score=3.3668063459999997&ReferrerJobPosition=8"
        }
    ],
    "freelancers": [
        {
            "type": "karlancer",
            "url": "https://www.karlancer.com/projects/%D9%BE%D8%B1%D9%88%DA%98%D9%87-%D8%AE%D8%A7%D9%86%D9%87-%D9%87%D9%88%D8%B4%D9%85%D9%86%D8%AF-2w6oom40m6ne",
            "title": "پروژه خانه هوشمند",
            "caption": "پروژه درباره ریزپردازنده و زبان اسمبلی هست ، باید یک خانه هوشمند با استفاده از شبیه ساز wokwi طراحی بشه توضیحات بیشتر در ادامه و بعد از توافق صورت میگیرد.",
            "salary": 800000,
            "image": null,
            "time": "۲۷ روز پیش",
            "owner": "کارفرمای جدید",
            "id": "https://www.karlancer.com/projects/%D9%BE%D8%B1%D9%88%DA%98%D9%87-%D8%AE%D8%A7%D9%86%D9%87-%D9%87%D9%88%D8%B4%D9%85%D9%86%D8%AF-2w6oom40m6ne"
        },
        {
            "type": "karlancer",
            "url": "https://www.karlancer.com/projects/%D8%A8%D8%B1%D8%B1%D8%B3%DB%8C-%D8%A7%D9%85%D9%86%DB%8C%D8%AA-74851nm2e823",
            "title": "بررسی امنیت",
            "caption": "چند تسک کوتاه که شامل دانش موارد زید میباشد:\nPhp\nOverflow\nDocker\nAssembly",
            "salary": 2500000,
            "image": null,
            "time": null,
            "owner": "کارفرمای جدید",
            "id": "https://www.karlancer.com/projects/%D8%A8%D8%B1%D8%B1%D8%B3%DB%8C-%D8%A7%D9%85%D9%86%DB%8C%D8%AA-74851nm2e823"
        },
        {
            "type": "karlancer",
            "url": "https://www.karlancer.com/projects/%D9%85%D8%AA%D8%AE%D8%B5%D8%B5-%D9%85%D9%87%D9%86%D8%AF%D8%B3%DB%8C-%D9%85%D8%B9%DA%A9%D9%88%D8%B3-%D9%86%D8%B1%D9%85-%D8%A7%D9%81%D8%B2%D8%A7%D8%B1-2m6m33133650",
            "title": "متخصص مهندسی معکوس نرم افزار",
            "caption": "سلام بنده به یک فردی که مهارت های زیر رو داشته باشه نیاز دارم:\nAssembly x86\nC++\nفرد باید بتونه یک برنامه رو مهندسی معکوس کنه",
            "salary": 10000000,
            "image": null,
            "time": null,
            "owner": "کارفرمای جدید",
            "id": "https://www.karlancer.com/projects/%D9%85%D8%AA%D8%AE%D8%B5%D8%B5-%D9%85%D9%87%D9%86%D8%AF%D8%B3%DB%8C-%D9%85%D8%B9%DA%A9%D9%88%D8%B3-%D9%86%D8%B1%D9%85-%D8%A7%D9%81%D8%B2%D8%A7%D8%B1-2m6m33133650"
        },
        {
            "type": "karlancer",
            "url": "https://www.karlancer.com/projects/%D9%86%DB%8C%D8%A7%D8%B2-%DB%8C%DA%A9-%D9%85%D8%AA%D8%AE%D8%B5%D8%B5-%D9%85%D9%87%D9%86%D8%AF%D8%B3%DB%8C-%D9%85%D8%B9%DA%A9%D9%88%D8%B3-2w6onr13o8ne",
            "title": "نیاز به یک متخصص مهندسی معکوس",
            "caption": "سلام.\nنیاز به یک متخصص دارای مهارت های زیر دارم:\nمسلط به x86 assembly\nC++\nشرط استخدام داشتن مهارت کامل در هردوی این موارد است.",
            "salary": 10000000,
            "image": null,
            "time": null,
            "owner": "کارفرمای جدید",
            "id": "https://www.karlancer.com/projects/%D9%86%DB%8C%D8%A7%D8%B2-%DB%8C%DA%A9-%D9%85%D8%AA%D8%AE%D8%B5%D8%B5-%D9%85%D9%87%D9%86%D8%AF%D8%B3%DB%8C-%D9%85%D8%B9%DA%A9%D9%88%D8%B3-2w6onr13o8ne"
        },
        {
            "type": "karlancer",
            "url": "https://www.karlancer.com/projects/%D8%A8%D8%B1%D9%86%D8%A7%D9%85%D9%87-%D9%86%D9%88%DB%8C%D8%B3%DB%8C-assembly-%D8%A8%D8%B1%D8%A7%DB%8Criskv-1n69mo32o62o",
            "title": "برنامه نویسی Assembly برایRISK-V",
            "caption": "لازم است این دو تسک حل شوند \nwrite a RISC_V assembly code for quick sort\nwrite a RISC-V assembly code for integer square root\nو کد و نتایج شبیه سازی دریافت شوند",
            "salary": 700000,
            "image": null,
            "time": null,
            "owner": "کارفرمای جدید",
            "id": "https://www.karlancer.com/projects/%D8%A8%D8%B1%D9%86%D8%A7%D9%85%D9%87-%D9%86%D9%88%DB%8C%D8%B3%DB%8C-assembly-%D8%A8%D8%B1%D8%A7%DB%8Criskv-1n69mo32o62o"
        },
        {
            "type": "karlancer",
            "url": "https://www.karlancer.com/projects/cswp-certificate-256453n3m8n0",
            "title": "CSWP certificate - SOLIDWORKS",
            "caption": "انجام CSWP CERTIFICATE که شامل 3 بخش طراحی به همراه محاسبه ی جرم، Creating configurations from other configurations و Creating an assembly می باشد.",
            "salary": 5000000,
            "image": null,
            "time": null,
            "owner": "کارفرمای جدید",
            "id": "https://www.karlancer.com/projects/cswp-certificate-256453n3m8n0"
        },
        {
            "type": "karlancer",
            "url": "https://www.karlancer.com/projects/%D9%BE%DB%8C%D8%A7%D8%AF%D9%87-%D8%B3%D8%A7%D8%B2%DB%8C-%D8%A7%D9%84%DA%A9%D9%88%D8%B1%DB%8C%D8%AA%D9%85%DB%8C-%D8%B2%D8%A8%D8%A7%D9%86-%D8%A7%D8%B3%D9%85%D8%A8%D9%84%DB%8C-906n1m5958ew",
            "title": "پیاده سازی الکوریتمی به زبان اسمبلی",
            "caption": "نیاز به پیاده سازی الکوریتمی به زبان اسمبلی هست. توضیحات تکمیلی خدمتتون ارسال میشه. به همراه گزارش کار نیاز دارم.",
            "salary": 600000,
            "image": null,
            "time": null,
            "owner": "کارفرمای جدید",
            "id": "https://www.karlancer.com/projects/%D9%BE%DB%8C%D8%A7%D8%AF%D9%87-%D8%B3%D8%A7%D8%B2%DB%8C-%D8%A7%D9%84%DA%A9%D9%88%D8%B1%DB%8C%D8%AA%D9%85%DB%8C-%D8%B2%D8%A8%D8%A7%D9%86-%D8%A7%D8%B3%D9%85%D8%A8%D9%84%DB%8C-906n1m5958ew"
        },
        {
            "type": "karlancer",
            "url": "https://www.karlancer.com/projects/%DA%A9%D8%B1%DA%A9-%D9%86%D8%B1%D9%85-%D8%A7%D9%81%D8%B2%D8%A7%D8%B1-motive-wave-6616-2m6m90e43650",
            "title": "استفاده از نرم افزار motive wave 6.6.16",
            "caption": "نیاز به استفاده از motive wave 6.6.15 در سطح کاربری ultimate edition داریم.\n\nدر این نسخه تمامی امکانات برنامه باز و قابل اجراست\n\nبرنامه برای ویندوز بر روی جاوا اجرا میشود\n\nmotive wave یک پلتفرم ترید در بازارهای مالی است\n\nنرم افزار دارای licence key هست",
            "salary": 5000000,
            "image": null,
            "time": null,
            "owner": "کارفرمای جدید",
            "id": "https://www.karlancer.com/projects/%DA%A9%D8%B1%DA%A9-%D9%86%D8%B1%D9%85-%D8%A7%D9%81%D8%B2%D8%A7%D8%B1-motive-wave-6616-2m6m90e43650"
        },
        {
            "type": "karlancer",
            "url": "https://www.karlancer.com/projects/%D8%B7%D8%B1%D8%A7%D8%AD%DB%8C-pcb-%D8%B4%D9%85%D8%A7%D8%AA%DB%8C%DA%A9-906n1n9n58ew",
            "title": "طراحی  PCB و شماتیک",
            "caption": "چندین پروژه طراحی pcb design به همراه شماتیک داریم.دو لایه تا 8 لایه.بعلاتوه یک سری کار pcb assembly و لحیم کاری. برای توضیحات بیشتر بهتره حضوری در مشهد گفتگو بشه.کار محدود به همین چند تا پروژه نیست و ما به دوستی نیاز داریم که بتونم پارت تایم همیشه باهاشون کار کنیم فقط اینکه حضور در شرکت در بعضی روزهای هفته لازمه",
            "salary": 8000000,
            "image": null,
            "time": null,
            "owner": "ناشناخته",
            "id": "https://www.karlancer.com/projects/%D8%B7%D8%B1%D8%A7%D8%AD%DB%8C-pcb-%D8%B4%D9%85%D8%A7%D8%AA%DB%8C%DA%A9-906n1n9n58ew"
        },
        {
            "type": "karlancer",
            "url": "https://www.karlancer.com/projects/%D9%BE%D8%B1%D9%88%DA%98%D9%87-%D8%B1%DB%8C%D8%B2%D9%BE%D8%B1%D8%AF%D8%A7%D8%B2%D9%86%D8%AF%D9%87-e7812wm0e6o1",
            "title": "پروژه ریزپردازنده",
            "caption": "سلام \nاین یک پروزه با زبان اسمبلی هست که باید\nبا استفاده از زبان اسمبلی، محیطی مانند  Paintشبیه سازی کنید.\nهمچنین برای پروژه یک گزارش کار نیز باید تهیه شود.\nفایل توضیحات پروژه به پیوست موجود می باشد.",
            "salary": 1000000,
            "image": null,
            "time": null,
            "owner": "کارفرمای جدید",
            "id": "https://www.karlancer.com/projects/%D9%BE%D8%B1%D9%88%DA%98%D9%87-%D8%B1%DB%8C%D8%B2%D9%BE%D8%B1%D8%AF%D8%A7%D8%B2%D9%86%D8%AF%D9%87-e7812wm0e6o1"
        },
        {
            "type": "karlancer",
            "url": "https://www.karlancer.com/projects/%D8%B7%D8%B1%D8%A7%D8%AD%DB%8C-%D9%85%DA%A9%D8%A7%D9%86%DB%8C%DA%A9%DB%8C-%D9%85%D8%A7%D8%B4%DB%8C%D9%86-%D8%B5%D9%86%D8%B9%D8%AA%DB%8C-%D9%88%DA%A9%DB%8C%D9%88%D9%85-%D9%81%D8%B1%D9%85%DB%8C%D9%86%DA%AF-%D8%B3%D8%A7%DB%8C%D8%B2-%D8%A8%D8%B2%D8%B1%DA%AF-m080wwwno64r",
            "title": "طراحی مکانیکی ماشین صنعتی وکیوم فرمینگ سایز بزرگ",
            "caption": "نیاز به یک طراح مکانیک برای طراحی یک دستگاه \nطراح باید با مکانیزم ها و المان های مکانیکی آشنایی مناسبی داشته باشد\nهدف، طراحی محصولی با ظرافت های بالا و عملکرد صنعتی است. \nمحیط مورد نظر برای طراحی نرم افزار سالیدورک است (Sheet metal, assembly, Feature)\nطراحی وکیوم فرمینگ سایز بزرگ حداکثر سایز 3000*3000\nشامل لود ورق آرکلیک\nهیتر دو طرفه برای گرم کردن ورق\nوکیوم ورق حداکثر عمق 1000 میلیمتر\nبا محاسبات و مشخص نمودن اندازه پروفیل ها و قطعات مصرفی در تولید ماشین",
            "salary": 5000000,
            "image": null,
            "time": null,
            "owner": "کارفرمای جدید",
            "id": "https://www.karlancer.com/projects/%D8%B7%D8%B1%D8%A7%D8%AD%DB%8C-%D9%85%DA%A9%D8%A7%D9%86%DB%8C%DA%A9%DB%8C-%D9%85%D8%A7%D8%B4%DB%8C%D9%86-%D8%B5%D9%86%D8%B9%D8%AA%DB%8C-%D9%88%DA%A9%DB%8C%D9%88%D9%85-%D9%81%D8%B1%D9%85%DB%8C%D9%86%DA%AF-%D8%B3%D8%A7%DB%8C%D8%B2-%D8%A8%D8%B2%D8%B1%DA%AF-m080wwwno64r"
        },
        {
            "type": "karlancer",
            "url": "https://www.karlancer.com/projects/%D8%B7%D8%B1%D8%A7%D8%AD%DB%8C-%D9%85%DA%A9%D8%A7%D9%86%DB%8C%DA%A9%DB%8C-%D9%85%D8%A7%D8%B4%DB%8C%D9%86-%D8%B5%D9%86%D8%B9%D8%AA%DB%8C-12m6m23o5850",
            "title": "طراحی مکانیکی ماشین صنعتی",
            "caption": "نیاز به یک طراح مکانیک برای طراحی یک دستگاه \nمنابع در دسترس برای طراحی پتنت ها و فیلم های یوتوب و کاتالوگ های دستگاه های مشابه است. \nطراح باید با مکانیزم ها و المان های مکانیکی آشنایی مناسبی داشته باشد\nهدف، طراحی محصولی با ظرافت های بالا و عملکرد صنعتی است. \nدر طراحی انواع روش های ساخت مکانیکی مانند ورق کاری، ماشین کاری CNC، برش لیزر و روش های مشابه مورد نظر است\nمحیط مورد نظر برای طراحی نرم افزار سالیدورک است (Sheet metal, assembly, Feature)",
            "salary": 5000000,
            "image": null,
            "time": null,
            "owner": "کارفرمای جدید",
            "id": "https://www.karlancer.com/projects/%D8%B7%D8%B1%D8%A7%D8%AD%DB%8C-%D9%85%DA%A9%D8%A7%D9%86%DB%8C%DA%A9%DB%8C-%D9%85%D8%A7%D8%B4%DB%8C%D9%86-%D8%B5%D9%86%D8%B9%D8%AA%DB%8C-12m6m23o5850"
        },
        {
            "type": "karlancer",
            "url": "https://www.karlancer.com/projects/%D8%B7%D8%B1%D8%AD-%D8%B1%DB%8C%D8%B2%DB%8C-%D9%88%D8%A7%D8%AD%D8%AF-%D9%87%D8%A7%DB%8C-%D8%B5%D9%86%D8%B9%D8%AA%DB%8C-r7485177m823",
            "title": "طرح ریزی واحد های صنعتی",
            "caption": "با سلام و احترام\n\nدر مورد درس طرح ریزی واحد ای صنعتی پروژه ای دارم که نیازمندم ، تهیه یک گزارش حداقل 10 صفحه ای با سایز 12 word با موضوعی به نام (طراحی از صفر / تغییر وطراحی مجدد سالنهای تولید یا ساخت و مونتاژ Manufacturing and Assembly در کارخانه هیوندا)\n\nلازم است در نوشتن این گزارش یک مقدمه ، چکیده، گزارش در حداکثر 200 کلمه بخش بندی و ارائه فهرست مطالب ، شماره صفحه گذاری، نوشان پانویس برای کلمات انگلیسی، گذاشتن شماره و عنوان برای اشکال و جداول و رعایت آیین نگارش و قوانین نقطه و ویرگول مورد توجه قرار گیرد",
            "salary": 500000,
            "image": null,
            "time": null,
            "owner": "کارفرمای جدید",
            "id": "https://www.karlancer.com/projects/%D8%B7%D8%B1%D8%AD-%D8%B1%DB%8C%D8%B2%DB%8C-%D9%88%D8%A7%D8%AD%D8%AF-%D9%87%D8%A7%DB%8C-%D8%B5%D9%86%D8%B9%D8%AA%DB%8C-r7485177m823"
        },
        {
            "type": "karlancer",
            "url": "https://www.karlancer.com/projects/%D8%B2%D8%A8%D8%A7%D9%86-%D8%A7%D8%B3%D9%85%D8%A8%D9%84%DB%8C-12m6m34m5650",
            "title": "زبان اسمبلی",
            "caption": "چند سوال اول که مربوط به برنامه نویسی زبان اسمبلی می باشد را کسی می خواهم که حل کند",
            "salary": 70000,
            "image": null,
            "time": null,
            "owner": "کارفرمای جدید",
            "id": "https://www.karlancer.com/projects/%D8%B2%D8%A8%D8%A7%D9%86-%D8%A7%D8%B3%D9%85%D8%A8%D9%84%DB%8C-12m6m34m5650"
        }
    ]
}